palmletRPA/__init__.py
palmletRPA/palmletRPA.cp38-win_amd64.pyd
palmletRPA/palmletRPA/__init__.pyi
palmletRPA/palmletRPA/excel.pyi
palmletRPA/palmletRPA/keyboard.pyi
palmletRPA/palmletRPA/mouse.pyi
palmletRPA/palmletRPA/requirements.txt
palmletRPA/palmletRPA/setup.pyi
palmletRPA/palmletRPA/ui_detect.pyi
palmletRPA/palmletRPA/web.pyi
palmletRPA/palmletRPA/win.pyi
palmletRPA/palmletRPA/db/auth.db
palmletRPA/palmletRPA/script/web_automation/stealth.min.js
palmletRPA-1.0.8.dist-info/METADATA
palmletRPA-1.0.8.dist-info/WHEEL
palmletRPA-1.0.8.dist-info/top_level.txt
palmletRPA-1.0.8.dist-info/RECORD
